{"expires":1756671417006,"value":{"code":200,"headers":{"etag":"W/\"lz7RgYAbrV\"","last-modified":"Sun, 24 Aug 2025 20:16:57 GMT","cache-control":"s-maxage=604800, stale-while-revalidate"},"body":{"prefix":"heroicons","icons":{"arrow-top-right-on-square":{"body":"<path fill=\"none\" stroke=\"currentColor\" stroke-linecap=\"round\" stroke-linejoin=\"round\" stroke-width=\"1.5\" d=\"M13.5 6H5.25A2.25 2.25 0 0 0 3 8.25v10.5A2.25 2.25 0 0 0 5.25 21h10.5A2.25 2.25 0 0 0 18 18.75V10.5m-10.5 6L21 3m0 0h-5.25M21 3v5.25\"/>"}},"lastModified":1721921294,"width":24,"height":24}},"mtime":1756066617007,"integrity":"maX4dISsQJ"}